inarrator/__init__.py
inarrator/email/__init__.py
inarrator/email/email.py
inarrator/email/message.py
inarrator/email/user.py
inarrator/exceptions.py
inarrator/summarizer/__init__.py
inarrator/summarizer/base.py
inarrator/summarizer/gpt.py
inarrator/summarizer/huggingface.py
inarrator/summarizer/prompt.py
inarrator/utils/__init__.py
inarrator/utils/util.py
inarrator-0.0.3.dist-info/LICENSE
inarrator-0.0.3.dist-info/METADATA
inarrator-0.0.3.dist-info/WHEEL
inarrator-0.0.3.dist-info/RECORD
