Metadata-Version: 2.1
Name: inarrator
Version: 0.0.3
Summary: Summarize and Narrate your emails through power of LLMs.
License: MIT
Author: keenborder786
Author-email: 21110290@lums.edu.pk
Requires-Python: >=3.8.1,<4.0
Classifier: License :: OSI Approved :: MIT License
Classifier: Programming Language :: Python :: 3
Classifier: Programming Language :: Python :: 3.9
Classifier: Programming Language :: Python :: 3.10
Classifier: Programming Language :: Python :: 3.11
Requires-Dist: google-api-python-client (>=2.97.0,<3.0.0)
Requires-Dist: google-auth-httplib2 (>=0.1.0,<0.2.0)
Requires-Dist: google-auth-oauthlib (>=1.0.0,<2.0.0)
Requires-Dist: html2text (>=2020.1.16,<2021.0.0)
Requires-Dist: langchain (>=0.0.265,<0.0.266)
Requires-Dist: msal (>=1.24.0,<2.0.0)
